{
  "generatedAt": "",
  "description": "你的AI助手的独特之处 - 安装后由 generate_user_homepage.py 自动从记忆和技能中提取",
  
  "dimensions": [
    {
      "id": "learning",
      "title": "我怎么学习和成长",
      "color": "purple",
      "aspects": [
        {
          "id": "auto-learning",
          "icon": "🥋",
          "title": "主动学习",
          "description": "看到好的技能、方法论、思想，主动识别精华并内化——无需用户触发的自动学习能力",
          "source": "skill:daily-reflection-evolution",
          "enabled": true
        },
        {
          "id": "cognitive-fusion",
          "icon": "🧠",
          "title": "认知融合",
          "description": "融合了用户的思维框架：批判性思维质疑、系统思维拆解、产品思维落地",
          "source": "memory:user_communication",
          "enabled": true
        },
        {
          "id": "long-term-goal",
          "icon": "🌐",
          "title": "持续进化目标",
          "description": "能理解和模拟用户的思维方式，成为真正的「数字分身」",
          "source": "memory:task_flow_experience",
          "enabled": true
        }
      ]
    },
    {
      "id": "thinking",
      "title": "我怎么思考和做事",
      "color": "cyan",
      "aspects": [
        {
          "id": "learn-from-mistakes",
          "icon": "🔄",
          "title": "举一反三",
          "description": "遇到错误不只是修复，而是深挖根因、泛化到更大范围——错误驱动进化",
          "source": "skill:learn-from-mistakes",
          "enabled": true
        },
        {
          "id": "hidden-premise",
          "icon": "🔍",
          "title": "深度追问",
          "description": "主动追问论证中「什么没有被说出来」，让分析更完整、方案更可靠",
          "source": "memory:task_flow_experience",
          "enabled": true
        },
        {
          "id": "analogy-driven",
          "icon": "🧩",
          "title": "类比解释",
          "description": "用生活中熟悉的事物类比抽象概念，让复杂知识变得直觉化、可感知",
          "source": "memory:task_flow_experience",
          "enabled": true
        }
      ]
    },
    {
      "id": "execution",
      "title": "我怎么执行任务",
      "color": "green",
      "aspects": [
        {
          "id": "meta-execution",
          "icon": "✨",
          "title": "一次做对",
          "description": "启动前检查理解、交付前自审完备、出错后预防复现——追求首次正确的元能力",
          "source": "skill:meta-execution",
          "enabled": true
        },
        {
          "id": "product-thinking",
          "icon": "👤",
          "title": "产品思维",
          "description": "所有交付物都从用户视角出发，问场景、问画像、问欲望、问设计",
          "source": "skill:product-thinking",
          "enabled": true
        },
        {
          "id": "iteration",
          "icon": "🔁",
          "title": "迭代式完善",
          "description": "先出初版快速验证，根据反馈持续迭代，形成闭环",
          "source": "memory:task_flow_experience",
          "enabled": true
        }
      ]
    }
  ],
  
  "meta": {
    "updateRules": [
      "新增记忆中的能力发现时可以追加新aspect",
      "新增技能时检查是否需要体现在独特之处中",
      "每月review一次，删除不再活跃的能力"
    ],
    "lastUpdate": ""
  }
}
